setup.py
ejabberd_python3d/__init__.py
ejabberd_python3d/client.py
ejabberd_python3d/serializers.py
ejabberd_python3d/abc/__init__.py
ejabberd_python3d/abc/api.py
ejabberd_python3d/abc/methods.py
ejabberd_python3d/core/__init__.py
ejabberd_python3d/core/errors.py
ejabberd_python3d/core/utils.py
ejabberd_python3d/defaults/__init__.py
ejabberd_python3d/defaults/arguments.py
ejabberd_python3d/defaults/constants.py
ejabberd_python3d/defaults/enums.py
ejabberd_python3d/ejabberd_auth/__init__.py
ejabberd_python3d/ejabberd_auth/management/__init__.py
ejabberd_python3d/ejabberd_auth/management/commands/__init__.py
ejabberd_python3d/ejabberd_auth/management/commands/ejabberd_auth.py
ejabberd_python3d/muc/__init__.py
ejabberd_python3d/muc/arguments.py
ejabberd_python3d/muc/enums.py
ejabberd_python3d/muc/serializers.py
ejabberd_python3d-0.2.3.dist-info/AUTHORS
ejabberd_python3d-0.2.3.dist-info/LICENSE
ejabberd_python3d-0.2.3.dist-info/METADATA
ejabberd_python3d-0.2.3.dist-info/WHEEL
ejabberd_python3d-0.2.3.dist-info/top_level.txt
ejabberd_python3d-0.2.3.dist-info/RECORD
